Metadata-Version: 2.1
Name: FrappePy
Version: 1.0.0
Summary: This is math base 
Home-page: https://github.com/twoj_username/nazwa_twojego_pakietu
Author: FrappePy Developers
Author-email: twoj_email@example.com
Classifier: Development Status :: 3 - Alpha
Classifier: Intended Audience :: Developers
Classifier: License :: OSI Approved :: MIT License
Classifier: Programming Language :: Python :: 3
Classifier: Programming Language :: Python :: 3.8
Classifier: Programming Language :: Python :: 3.9
Classifier: Programming Language :: Python :: 3.10
Classifier: Programming Language :: Python :: 3.11
Classifier: Programming Language :: Python :: 3.12
Requires-Python: >=3.12
Requires-Dist: numpy>=1.19.2
Requires-Dist: requests>=2.24.0
